{
  "content":[{"_id":"59b1555e5aa1fb518ba5a0ba","firstName":"กรกมล","lastName":"ศรีวัฒน์","interviewRef":"CT07"},{"_id":"59b64e53f68e725d33fe068f","firstName":"กริษฐา","lastName":"นาคะรังสุ","interviewRef":"CT55"},{"_id":"59f895bcef4bb30451d0e1ef","firstName":"กุลธิดา","lastName":"กันต์พิทยา","interviewRef":"CT18"},{"_id":"59b23f665aa1fb518ba5a286","firstName":"จิราพัชร ","lastName":"เหลืองอร่ามกุล","interviewRef":"CT44"},{"_id":"59f31f4cef4bb30451d0d9d7","firstName":"จุฑารัตน์","lastName":"นิลวงษ์","interviewRef":"CT29"},{"_id":"59b24dab5aa1fb518ba5a29e","firstName":"จุรีภรณ์","lastName":"พวงน้อย","interviewRef":"CT50"},{"_id":"59fdd22c5dd63d4bd5ba9549","firstName":"ชนิกานต์","lastName":"พันธ์ชนะ","interviewRef":"CT09"},{"_id":"5a0431765dd63d4bd5baa874","firstName":"ชัญญา","lastName":"ระตะนะอาพร","interviewRef":"CT52"},{"_id":"59bd6e3da4fa985d2dd8a015","firstName":"ณัฐนนท์","lastName":"ดวงสูงเนิน","interviewRef":"CT28"},{"_id":"59dcd63954c7736f271ac44c","firstName":"นลินี","lastName":"พาณิชย์เจริญใจ","interviewRef":"CT08"},{"_id":"59e0abba7d0f5a6f21a6c344","firstName":"ภรพฤกษา","lastName":"อาศัยธรรมกุล","interviewRef":"CT43"},{"_id":"59d7b83c49fc310b74d52f70","firstName":"วราพร","lastName":"ลี้เลิศล้ำ","interviewRef":"CT25"},{"_id":"59b154c75aa1fb518ba5a0b7","firstName":"ศุภาพิชญ์","lastName":"หงษ์สวัสดิ์","interviewRef":"CT41"},{"_id":"59b3e7eef68e725d33fe05a0","firstName":"สรญา","lastName":"อุดมมิตรรัก","interviewRef":"CT06"},{"_id":"59c31ec8a4fa985d2dd8a151","firstName":"สามฟ้า","lastName":"เขมะวิชานุรัตน์","interviewRef":"CT48"},{"_id":"59ff33915dd63d4bd5baa058","firstName":"สุภาณี","lastName":"ลิ้มโรจน์นุกูล","interviewRef":"CT26"},{"_id":"59b1794636dab95186a9f61c","firstName":"อณวิทย์","lastName":"จิตรมานะ","interviewRef":"CT13"},{"_id":"59f59cae188073045766b158","firstName":"อรอินทุ์","lastName":"ฐานถิร","interviewRef":"CT12"},{"_id":"59b2e5595aa1fb518ba5a358","firstName":"อัคราธร","lastName":"เอี่ยมศรี","interviewRef":"CT21"},{"_id":"59db276ea795523adb29d346","firstName":"อานนท์","lastName":"บำรุงศิริ","interviewRef":"CT38"}],
  "marketing": [{"_id":"59b255fa5aa1fb518ba5a2a8","firstName":"กมลณัฐ","lastName":"ศรีอุดร","interviewRef":"MK43"},{"_id":"59d76bd7cb7c620b6e200225","firstName":"กานต์สิณี","lastName":"ชาญสิทธิ์","interviewRef":"MK13"},{"_id":"59d2765270246737a962057b","firstName":"กิตติพัฒน์","lastName":"วงษ์ล้วนงาม","interviewRef":"MK37"},{"_id":"59b2a58d5aa1fb518ba5a2f6","firstName":"กิตติโชติ","lastName":"ถิรผดุงพงศ์","interviewRef":"MK17"},{"_id":"59b35a005aa1fb518ba5a36d","firstName":"ชญานิน","lastName":"ประศมศานติ์","interviewRef":"MK39"},{"_id":"59f0d325ef4bb30451d0d871","firstName":"ชัยชนะ ","lastName":"อนุรักษ์จาตุรงค์","interviewRef":"MK29"},{"_id":"59f70ec2ef4bb30451d0de68","firstName":"ชัยวิวัฒน์","lastName":"อัครหิรัญสกุล","interviewRef":"MK38"},{"_id":"59bad149a4fa985d2dd89fb8","firstName":"ณัฐพล","lastName":"ขาววิสุทธิ์","interviewRef":"MK04"},{"_id":"59b3568a5aa1fb518ba5a36b","firstName":"ธนียา","lastName":"ตันติสาธิต","interviewRef":"MK47"},{"_id":"59ce28f616074c7ea94750cf","firstName":"ธันยรัศมิ์","lastName":"ช่อเพ็ชรไทย","interviewRef":"MK27"},{"_id":"59b168f15aa1fb518ba5a120","firstName":"นิธิพงศ์","lastName":"ใจทา","interviewRef":"MK09"},{"_id":"59ff1d0f5dd63d4bd5ba9df3","firstName":"พิสิฐ","lastName":"ซื่อวิริยพันธุ์","interviewRef":"MK18"},{"_id":"59c05b58a4fa985d2dd8a074","firstName":"รัชพล","lastName":"งามนิธิพร","interviewRef":"MK06"},{"_id":"59fc70605dd63d4bd5ba91c4","firstName":"รุ้งพิวรรณ","lastName":"แซ่ตั้ง","interviewRef":"MK40"},{"_id":"59bd2036a4fa985d2dd8a00a","firstName":"วชิตะ","lastName":"จ่ายพอควร","interviewRef":"MK20"},{"_id":"59ff0ffb5dd63d4bd5ba9cd8","firstName":"วทันยา","lastName":"เกษตระทัต","interviewRef":"MK08"},{"_id":"59b22d3b36dab95186a9f702","firstName":"สฐิปกรณ์","lastName":"วิบูลย์ประพันธ์","interviewRef":"MK49"},{"_id":"59d34b7d94458a3bed48aade","firstName":"สิริกาญจน์","lastName":"เชื่อมสุวรรณ","interviewRef":"MK48"},{"_id":"59ed63c1188073045766acab","firstName":"สุทัศน์","lastName":"ดาวเชิญ","interviewRef":"MK23"},{"_id":"59b4cb22a4fa985d2dd89dff","firstName":"สุภัททิยา","lastName":"ลีลาทิพย์กุล","interviewRef":"MK10"}],
  "programming": [{"_id":"59f73152ef4bb30451d0def4","firstName":"กองภณ","lastName":"จรัญวัฒนากิจ","interviewRef":"PG39"},{"_id":"59f90bf80e65f62dcf1ed808","firstName":"กัญจนสิทธ","lastName":"ทองเล็ก","interviewRef":"PG31"},{"_id":"59fb33a60e65f62dcf1edb14","firstName":"จักรี","lastName":"โล่พันธุ์ศิริกุล","interviewRef":"PG02"},{"_id":"59b6a880a4fa985d2dd89ead","firstName":"ชินาธิป","lastName":"วิเชียร","interviewRef":"PG38"},{"_id":"59b20d3d36dab95186a9f6cb","firstName":"ณัฐภัทร","lastName":"สุขภูตานันท์","interviewRef":"PG06"},{"_id":"59d7341acb7c620b6e200202","firstName":"ตุลธร","lastName":"ศรีพงษ์พันธุ์กุล","interviewRef":"PG37"},{"_id":"59b1658a5aa1fb518ba5a106","firstName":"ธรรมนูญ","lastName":"โจมจตุรงค์","interviewRef":"PG61"},{"_id":"59fae6d9c90d0c2dd5522ee4","firstName":"ปฐมพงศ์","lastName":"ไชยศรี","interviewRef":"PG03"},{"_id":"59b2b7fe5aa1fb518ba5a315","firstName":"ปัญญาวุธ","lastName":"ศรีอิสรานุสรณ์","interviewRef":"PG62"},{"_id":"59bd3f38a4fa985d2dd8a00d","firstName":"มนัสวีร์","lastName":"เทพกิจอารีกุล","interviewRef":"PG58"},{"_id":"59b15ef136dab95186a9f588","firstName":"รพีพัฒน์","lastName":"แก้วประสิทธิ์","interviewRef":"PG44"},{"_id":"59fc76e25dd63d4bd5ba91cc","firstName":"ราชศักดิ์","lastName":"รักษ์กำเนิด","interviewRef":"PG09"},{"_id":"59f01616ef4bb30451d0d7e1","firstName":"วศิน","lastName":"วัฒนศรีส่ง","interviewRef":"PG33"},{"_id":"59e8d316e6583f3eab2021e9","firstName":"วิศรุจ","lastName":"ภู่เสือ","interviewRef":"PG17"},{"_id":"59bd4ff9a4fa985d2dd8a010","firstName":"ศกานต์","lastName":"โกมลวาทิน","interviewRef":"PG54"},{"_id":"59f6257cef4bb30451d0dd0d","firstName":"สุรดิษ","lastName":"จ้าว","interviewRef":"PG05"},{"_id":"59b1562d36dab95186a9f562","firstName":"อริญชย์","lastName":"ตรงสันติพงศ์","interviewRef":"PG47"},{"_id":"59e351a8972cd9541968d6fb","firstName":"อุดมทรัพย์","lastName":"หน่ายคอน","interviewRef":"PG10"},{"_id":"5a02b2e85dd63d4bd5baa743","firstName":"เรียวไผ่","lastName":"จันทร์สร้อย","interviewRef":"PG41"},{"_id":"59b1a8405aa1fb518ba5a1c4","firstName":"เอกลักษณ์","lastName":"ลีละศรชัย","interviewRef":"PG04"}],
  "design": []
}